ShellUtilities/Shell.py
ShellUtilities/ShellCommandException.py
ShellUtilities/ShellCommandResults.py
ShellUtilities/__init__.py
ShellUtilities-2.1.14.dist-info/METADATA
ShellUtilities-2.1.14.dist-info/WHEEL
ShellUtilities-2.1.14.dist-info/top_level.txt
ShellUtilities-2.1.14.dist-info/RECORD
