Metadata-Version: 2.1
Name: ShellUtilities
Version: 2.1.14
Summary: A library for executing shell commands in either a blocking or non-blocking way.
Home-page: https://github.com/taylor-schneider/ShellUtilities
Author: tschneider
Author-email: tschneider@live.com
Classifier: Programming Language :: Python :: 3
Classifier: License :: OSI Approved :: GNU General Public License v3 (GPLv3)
Classifier: Operating System :: OS Independent
